osintplus/__init__.py
osintplus/cli.py
osintplus/core.py
osintplus/utils.py
osintplus-0.1.1.dist-info/licenses/LICENSE
osintplus-0.1.1.dist-info/METADATA
osintplus-0.1.1.dist-info/WHEEL
osintplus-0.1.1.dist-info/entry_points.txt
osintplus-0.1.1.dist-info/top_level.txt
osintplus-0.1.1.dist-info/RECORD
