Metadata-Version: 2.4
Name: osintplus
Version: 0.1.1
Summary: Outil de renseignement OSINT en ligne de commande, sans utiliser d'API
Home-page: https://github.com/hakersgenie/osintplus
Author: root10
License: MIT
Keywords: osint,cli,reconnaissance,cybersecurity
Classifier: Programming Language :: Python :: 3
Classifier: License :: OSI Approved :: MIT License
Classifier: Operating System :: OS Independent
Requires-Python: >=3.7
License-File: LICENSE
Requires-Dist: requests
Requires-Dist: python-whois
Requires-Dist: colorama
Requires-Dist: tqdm
Dynamic: home-page
Dynamic: license-file
